AUTHORS.rst
CHANGELOG.rst
MANIFEST.in
README.rst
setup.py
django_mobiclicks.egg-info/PKG-INFO
django_mobiclicks.egg-info/SOURCES.txt
django_mobiclicks.egg-info/dependency_links.txt
django_mobiclicks.egg-info/not-zip-safe
django_mobiclicks.egg-info/requires.txt
django_mobiclicks.egg-info/top_level.txt
mobiclicks/__init__.py
mobiclicks/conf.py
mobiclicks/middleware.py
mobiclicks/models.py
mobiclicks/tasks.py
mobiclicks/tests.py